agent360/__init__.py
agent360/agent360.py
agent360/plugins/__init__.py
agent360/plugins/apt-updates.py
agent360/plugins/asterisk.py
agent360/plugins/bind.py
agent360/plugins/bird.py
agent360/plugins/bitninja.py
agent360/plugins/cloudlinux-dbgov.py
agent360/plugins/cloudlinux.py
agent360/plugins/cpanel.py
agent360/plugins/cpu.py
agent360/plugins/cpu_freq.py
agent360/plugins/dirsize.py
agent360/plugins/diskinodes.py
agent360/plugins/diskstatus-nvme.py
agent360/plugins/diskstatus.py
agent360/plugins/diskusage.py
agent360/plugins/docker.py
agent360/plugins/dovecot.py
agent360/plugins/elasticsearch.py
agent360/plugins/exim.py
agent360/plugins/fail2ban.py
agent360/plugins/gpu.py
agent360/plugins/haproxy.py
agent360/plugins/httpd.py
agent360/plugins/iostat.py
agent360/plugins/janus.py
agent360/plugins/kamailio.py
agent360/plugins/litespeed.py
agent360/plugins/loadavg.py
agent360/plugins/loggedin.py
agent360/plugins/mailq.py
agent360/plugins/mdstat.py
agent360/plugins/megacli.py
agent360/plugins/memcached.py
agent360/plugins/memory.py
agent360/plugins/minecraft.py
agent360/plugins/mongodb.py
agent360/plugins/mysql.py
agent360/plugins/network.py
agent360/plugins/nginx.py
agent360/plugins/openvpn.py
agent360/plugins/phpfpm.py
agent360/plugins/ping.py
agent360/plugins/plesk-cgroups.py
agent360/plugins/plugins-installer.py
agent360/plugins/plugins.py
agent360/plugins/postfix.py
agent360/plugins/powerdns.py
agent360/plugins/process.py
agent360/plugins/proftpd.py
agent360/plugins/rabbitmq.py
agent360/plugins/redis_stat.py
agent360/plugins/sleeper.py
agent360/plugins/swap.py
agent360/plugins/system.py
agent360/plugins/tcpports.py
agent360/plugins/temp.py
agent360/plugins/unbound.py
agent360/plugins/vms.py
agent360/plugins/wp-toolkit.py
agent360/plugins/yum-updates.py
agent360-1.3.4.data/data/share/doc/agent360/LICENSE
agent360-1.3.4.data/data/share/doc/agent360/README.md
agent360-1.3.4.data/data/share/doc/agent360/agent360-example.ini
agent360-1.3.4.dist-info/LICENSE
agent360-1.3.4.dist-info/METADATA
agent360-1.3.4.dist-info/WHEEL
agent360-1.3.4.dist-info/entry_points.txt
agent360-1.3.4.dist-info/top_level.txt
agent360-1.3.4.dist-info/RECORD
