Metadata-Version: 2.1
Name: agent360
Version: 1.3.4
Summary: 360 agent
Home-page: https://github.com/plesk/agent360
Author: 360
Author-email: 360support@webpros.com
Maintainer: 360
Maintainer-email: 360support@webpros.com
License: BSD-3-Clause
Keywords: 360 system monitoring agent
Classifier: Development Status :: 5 - Production/Stable
Classifier: Environment :: No Input/Output (Daemon)
Classifier: Intended Audience :: System Administrators
Classifier: License :: OSI Approved :: BSD License
Classifier: Natural Language :: English
Classifier: Operating System :: POSIX :: Linux
Classifier: Programming Language :: Python :: 2.7
Classifier: Programming Language :: Python :: 3.4
Classifier: Programming Language :: Python :: 3.5
Classifier: Programming Language :: Python :: 3.6
Classifier: Topic :: System :: Monitoring
License-File: LICENSE
Requires-Dist: psutil
Requires-Dist: netifaces
Requires-Dist: configparser
Requires-Dist: future
Requires-Dist: distro
Requires-Dist: certifi
